pyfilecrypto/__init__.py
pyfilecrypto/crypto.py
pyfilecrypto-1.0.3.dist-info/LICENSE.md
pyfilecrypto-1.0.3.dist-info/METADATA
pyfilecrypto-1.0.3.dist-info/WHEEL
pyfilecrypto-1.0.3.dist-info/top_level.txt
pyfilecrypto-1.0.3.dist-info/RECORD
