Metadata-Version: 2.1
Name: pyfilecrypto
Version: 1.0.3
Summary: A module for file encryption and decryption
Home-page: https://github.com/zshn1248/pyfilecrypto
Author: Muhammad Zeeshan Saeed
Author-email: zshn1248@gmail.com
Classifier: Programming Language :: Python :: 3
Classifier: License :: OSI Approved :: MIT License
Classifier: Operating System :: OS Independent
Requires-Python: >=3.6
License-File: LICENSE.md
Requires-Dist: cryptography
Requires-Dist: pyzipper
